dorton/__init__.py
dorton/app.py
dorton/exceptions.py
dorton/http/__init__.py
dorton/http/enums.py
dorton/http/request.py
dorton/http/response.py
Dorton-0.0.1.1.dist-info/METADATA
Dorton-0.0.1.1.dist-info/WHEEL
Dorton-0.0.1.1.dist-info/top_level.txt
Dorton-0.0.1.1.dist-info/RECORD
