Metadata-Version: 2.1
Name: Dorton
Version: 0.0.1.1
Summary: Python Lightweight Framework
Home-page: UNKNOWN
Author: wariored
Author-email: cheikh@cheikhkonteye.com
License: UNKNOWN
Platform: UNKNOWN
Classifier: Programming Language :: Python :: 3
Classifier: License :: OSI Approved :: MIT License
Classifier: Operating System :: OS Independent
Requires-Python: >=3.9
